[ 
  {"name": "Österreich", "code": "AT"}, 
  {"name": "Belgien", "code": "BE"}, 
  {"name": "Bulgarien", "code": "BG"}, 
  {"name": "Kroatien", "code": "HR"}, 
  {"name": "Zypern", "code": "CY"}, 
  {"name": "Tschechien", "code": "CZ"}, 
  {"name": "Dänemark", "code": "DK"}, 
  {"name": "Estland", "code": "EE"}, 
  {"name": "Finnland", "code": "FI"}, 
  {"name": "Frankreich", "code": "FR"}, 
  {"name": "Deutschland", "code": "DE"}, 
  {"name": "Griechenland", "code": "GR"}, 
  {"name": "Ungarn", "code": "HU"}, 
  {"name": "Irland", "code": "IE"}, 
  {"name": "Italien", "code": "IT"}, 
  {"name": "Lettland", "code": "LV"}, 
  {"name": "Litauen", "code": "LT"}, 
  {"name": "Luxemburg", "code": "LU"}, 
  {"name": "Malta", "code": "MT"}, 
  {"name": "Niederlande", "code": "NL"}, 
  {"name": "Polen", "code": "PL"}, 
  {"name": "Portugal", "code": "PT"}, 
  {"name": "Rumänien", "code": "RO"}, 
  {"name": "Slowakei", "code": "SK"}, 
  {"name": "Slowenien", "code": "SI"}, 
  {"name": "Spanien", "code": "ES"}, 
  {"name": "Schweden", "code": "SE"}, 
  {"name": "Vereinigtes Königreich", "code": "GB"}
]
